mt5_order_handle/__init__.py
mt5_order_handle/mt5order.py
mt5_order_handle-1.0.1.dist-info/LICENSE.txt
mt5_order_handle-1.0.1.dist-info/METADATA
mt5_order_handle-1.0.1.dist-info/WHEEL
mt5_order_handle-1.0.1.dist-info/top_level.txt
mt5_order_handle-1.0.1.dist-info/RECORD
