Metadata-Version: 2.1
Name: mt5-order-handle
Version: 1.0.1
Summary: a package that contain python function for handle mt5 order
Home-page: UNKNOWN
Author: Kritthanit_Malathong
Author-email: kritthanit.m@gmail.com
License: UNKNOWN
Platform: UNKNOWN
Classifier: Programming Language :: Python :: 3
Classifier: License :: OSI Approved :: MIT License
Classifier: Operating System :: OS Independent
Requires-Python: >=3.9
License-File: LICENSE.txt
Requires-Dist: MetaTrader5
Requires-Dist: pandas
Requires-Dist: datetime
